AUTHORS.rst
HISTORY.rst
MANIFEST.in
README.md
setup.py
bin/zdsindicator
zdsindicator/GConf.py
zdsindicator/__init__.py
zdsindicator/authentication_dialog.py
zdsindicator/configure_dialog.py
zdsindicator/zindicator.py
zdsindicator/znotification.py
zdsindicator/zparsing.py
zdsindicator/zrequest.py
zdsindicator/zthread.py
zdsindicator.egg-info/PKG-INFO
zdsindicator.egg-info/SOURCES.txt
zdsindicator.egg-info/dependency_links.txt
zdsindicator.egg-info/not-zip-safe
zdsindicator.egg-info/requires.txt
zdsindicator.egg-info/top_level.txt
zdsindicator/icons/zdsindicator-forums.png
zdsindicator/icons/zdsindicator-icon.png
zdsindicator/icons/zdsindicator-logout.png
zdsindicator/icons/zdsindicator-mp.png
zdsindicator/icons/zdsindicator-parsing.png