Metadata-Version: 1.0
Name: zdsindicator
Version: 0.0.1
Summary: Un applet ubuntu pour le site Zeste de Savoir
Home-page: https://github.com/poulp/zdsindicator
Author: poulp
Author-email: mathieu.nerv@gmail.com
License: BSD
Keywords: zdsindicator
Platform: UNKNOWN
